MANIFEST.in
README
setup.py
Struqtural.egg-info/PKG-INFO
Struqtural.egg-info/SOURCES.txt
Struqtural.egg-info/dependency_links.txt
Struqtural.egg-info/top_level.txt
struqtural/__init__.py
struqtural/basetypes.py
struqtural/instances.py
struqtural/utilities.py
struqtural/database/__init__.py
struqtural/database/comparator.py
struqtural/database/connector.py
struqtural/database/extension.py
struqtural/database/metadata.py
struqtural/database/query.py
struqtural/database/relationship.py
struqtural/database/utilities.py
struqtural/loaders/__init__.py
struqtural/loaders/eav.py
struqtural/loaders/file.py
struqtural/loaders/graph.py
struqtural/loaders/loader.py
struqtural/mixins/__init__.py
struqtural/mixins/mixin.py
struqtural/mixins/numeric.py
struqtural/mixins/units.py
struqtural/processes/__init__.py
struqtural/processes/files.py
struqtural/processes/graph.py
struqtural/processes/introspection.py
struqtural/processes/language.py
struqtural/processes/typeinference.py
struqtural/resources/sql_server.cfg
struqtural/structures/__init__.py
struqtural/structures/eav.py
struqtural/structures/graph.py
struqtural/structures/structure.py
tests/__init__.py
tests/test_database.py
tests/test_loaders.py
tests/test_mixins.py
tests/test_primitives.py
tests/test_processes.py
tests/data/cd_catalog.xml
tests/data/complex_sales_order.xml
tests/data/department.xml
tests/data/menu.xml
tests/data/sales_order.xml
tests/structures/__init__.py
tests/structures/test_array.py
tests/structures/test_eav.py
tests/structures/test_graph.py