Metadata-Version: 1.1
Name: Struqtural
Version: 0.1
Summary: High level SQL structure manipulation library
Home-page: http://www.turnkey-analytics.com/struqtural/
Author: Nathan Rice
Author-email: nathan.alexander.rice@gmail.com
License: UNKNOWN
Platform: UNKNOWN
Classifier: Development Status :: 4 - Beta
Classifier: Environment :: Console
Classifier: Environment :: Web Environment
Classifier: Intended Audience :: Information Technology
Classifier: Intended Audience :: Developers
Classifier: Intended Audience :: Science/Research
Classifier: Topic :: Database
Classifier: Topic :: Software Development :: Libraries
Classifier: License :: OSI Approved :: Python Software Foundation License
Classifier: Operating System :: MacOS :: MacOS X
Classifier: Operating System :: Microsoft :: Windows
Classifier: Operating System :: POSIX
Classifier: Programming Language :: Python
Requires: sqlalchemy
Requires: decorator
